KVDatastore/__init__.py
KVDatastore-1.0.1.dist-info/LICENCE.txt
KVDatastore-1.0.1.dist-info/METADATA
KVDatastore-1.0.1.dist-info/WHEEL
KVDatastore-1.0.1.dist-info/top_level.txt
KVDatastore-1.0.1.dist-info/RECORD
