Metadata-Version: 2.1
Name: KVDatastore
Version: 1.0.1
Summary: File based key-value datastore
Home-page: UNKNOWN
Author: Jeffry Joseph
Author-email: jeffryjoseph116@gmail.com
License: MIT
Keywords: key-value datastore
Platform: UNKNOWN
Classifier: Development Status :: 5 - Production/Stable
Classifier: Intended Audience :: Education
Classifier: Operating System :: Microsoft :: Windows :: Windows 10
Classifier: License :: OSI Approved :: MIT License
Classifier: Programming Language :: Python :: 3
